Metadata-Version: 1.0
Name: pickleparser
Version: 0.5
Summary: A tool to preview pickle or jsonpickle content
Home-page: https://github.com/tumb1er/pickleparser/
Author: tumbler
Author-email: zimbler@gmail.com
License: Beer license
Platform: UNKNOWN
